noizu_ops/__init__.py
noizu_ops/bin/__init__.py
noizu_ops/bin/noizu_ops.py
noizu_ops/config/system_config.fallback.yml
noizu_ops/setup/__init__.py
noizu_ops/setup/noizu_help_init.py
noizu_ops-0.1.1.dist-info/LICENSE
noizu_ops-0.1.1.dist-info/METADATA
noizu_ops-0.1.1.dist-info/WHEEL
noizu_ops-0.1.1.dist-info/entry_points.txt
noizu_ops-0.1.1.dist-info/top_level.txt
noizu_ops-0.1.1.dist-info/RECORD
